pysonofflan/__init__.py
pysonofflan/cli.py
pysonofflan/client.py
pysonofflan/discover.py
pysonofflan/sonoffdevice.py
pysonofflan/sonoffswitch.py
pysonofflan-0.3.0.dist-info/AUTHORS.rst
pysonofflan-0.3.0.dist-info/LICENSE
pysonofflan-0.3.0.dist-info/METADATA
pysonofflan-0.3.0.dist-info/WHEEL
pysonofflan-0.3.0.dist-info/entry_points.txt
pysonofflan-0.3.0.dist-info/top_level.txt
pysonofflan-0.3.0.dist-info/RECORD
