Metadata-Version: 2.1
Name: pysonofflan
Version: 0.3.0
Summary: Interface for Sonoff devices running original Itead firmware, in LAN mode.
Home-page: https://github.com/beveradb/pysonofflan
Author: Andrew Beveridge
Author-email: andrew@beveridge.uk
License: MIT license
Keywords: pysonofflan
Platform: UNKNOWN
Classifier: Development Status :: 2 - Pre-Alpha
Classifier: Intended Audience :: Developers
Classifier: License :: OSI Approved :: MIT License
Classifier: Natural Language :: English
Classifier: Programming Language :: Python :: 3.5
Classifier: Programming Language :: Python :: 3.6
Classifier: Programming Language :: Python :: 3.7
Requires-Dist: Click (>=7.0)
Requires-Dist: click-log
Requires-Dist: websockets
